{
	"storyName": "Dave The Racist Gamer",
	"difficulties": "Hard",
	"hideFreeplay": false,
	"weekBackground": "studioshalloween",
	"freeplayColor": [
		146,
		113,
		253
	],
	"weekBefore": "Studios2",
	"startUnlocked": false,
	"weekCharacters": [
		"",
		"",
		""
	],
	"songs": [
		[
			"Dotcom",
			"dave",
			[
				40,
				40,
				100
			]
		],
		[
			"Gaming",
			"dave",
			[
				40,
				40,
				100
			]
		],
		[
			"Hacks",
			"hacz",
			[
				40,
				40,
				100
			]
		]
	],
	"hideStoryMode": false,
	"weekName": "Studios3"
}